cpplint.py
agora_cpplint-1.6.1.dist-info/LICENSE
agora_cpplint-1.6.1.dist-info/METADATA
agora_cpplint-1.6.1.dist-info/WHEEL
agora_cpplint-1.6.1.dist-info/entry_points.txt
agora_cpplint-1.6.1.dist-info/top_level.txt
agora_cpplint-1.6.1.dist-info/RECORD
