Metadata-Version: 2.1
Name: agora-cpplint
Version: 1.6.1
Summary: Automated checker to ensure C++ files follow Google's style guide
Home-page: https://github.com/imagora/agora-cpplint
Download-URL: https://github.com/imagora/agora-cpplint
Maintainer: cpplint Developers
Maintainer-email: winking324@gmail.com
License: BSD-3-Clause
Keywords: lint,python,c++
Classifier: Programming Language :: Python
Classifier: Programming Language :: Python :: 2
Classifier: Programming Language :: Python :: 2.7
Classifier: Programming Language :: Python :: 3
Classifier: Programming Language :: Python :: 3.6
Classifier: Programming Language :: Python :: 3.7
Classifier: Programming Language :: Python :: 3.8
Classifier: Programming Language :: C++
Classifier: Development Status :: 5 - Production/Stable
Classifier: Environment :: Console
Classifier: Topic :: Software Development :: Quality Assurance
Classifier: License :: Freely Distributable
License-File: LICENSE
Provides-Extra: dev
Requires-Dist: flake8 (>=4.0.1) ; extra == 'dev'
Requires-Dist: flake8-polyfill ; extra == 'dev'
Requires-Dist: pylint (>=2.11.0) ; extra == 'dev'
Requires-Dist: tox (>=3.0.0) ; extra == 'dev'
Requires-Dist: tox-pyenv ; extra == 'dev'
Requires-Dist: importlib-metadata (>=0.12) ; extra == 'dev'
Requires-Dist: pytest (<5.0,>=4.6) ; extra == 'dev'
Requires-Dist: pytest-cov ; extra == 'dev'
Requires-Dist: pyparsing (<3) ; extra == 'dev'
Requires-Dist: zipp (<=0.5.1) ; extra == 'dev'
Requires-Dist: configparser (<=3.7.4) ; extra == 'dev'
Requires-Dist: testfixtures ; extra == 'dev'
Provides-Extra: test
Requires-Dist: pytest (<5.0,>=4.6) ; extra == 'test'
Requires-Dist: pytest-cov ; extra == 'test'
Requires-Dist: pyparsing (<3) ; extra == 'test'
Requires-Dist: zipp (<=0.5.1) ; extra == 'test'
Requires-Dist: configparser (<=3.7.4) ; extra == 'test'
Requires-Dist: testfixtures ; extra == 'test'
